alactic_agi/__init__.py
alactic_agi/__version__.py
alactic_agi/cli.py
alactic_agi/core.py
alactic_agi/crawler.py
alactic_agi/demo.py
alactic_agi/framework.py
alactic_agi/indexer.py
alactic_agi/monitoring.py
alactic_agi/validator.py
alactic_agi/config/default.ini
alactic_agi-1.0.0.dist-info/licenses/LICENSE
alactic_agi-1.0.0.dist-info/METADATA
alactic_agi-1.0.0.dist-info/WHEEL
alactic_agi-1.0.0.dist-info/entry_points.txt
alactic_agi-1.0.0.dist-info/top_level.txt
alactic_agi-1.0.0.dist-info/RECORD
