Metadata-Version: 2.4
Name: alactic-agi
Version: 1.0.0
Summary: Enterprise AI Dataset Processing Platform - Scalable data acquisition, validation, and structuring with production-ready monitoring
Home-page: https://github.com/AlacticAI/alactic-agi
Author: Yash Parashar
Author-email: Yash Parashar <yash@alacticai.com>, "Alactic Inc." <support@alacticai.com>
Maintainer-email: Yash Parashar <yash@alacticai.com>
License: MIT
Project-URL: Homepage, https://www.alacticai.com
Project-URL: Documentation, https://docs.alacticai.com
Project-URL: Repository, https://github.com/AlacticAI/alactic-agi
Project-URL: Bug Tracker, https://github.com/AlacticAI/alactic-agi/issues
Project-URL: Changelog, https://github.com/AlacticAI/alactic-agi/blob/main/CHANGELOG.md
Project-URL: Commercial Support, https://www.alacticai.com
Keywords: ai,dataset,processing,scraping,monitoring,enterprise,solr,prometheus,data-pipeline,machine-learning,web-crawling,data-validation
Classifier: Development Status :: 5 - Production/Stable
Classifier: Intended Audience :: Developers
Classifier: Intended Audience :: Science/Research
Classifier: Intended Audience :: Information Technology
Classifier: License :: OSI Approved :: MIT License
Classifier: Operating System :: OS Independent
Classifier: Programming Language :: Python :: 3
Classifier: Programming Language :: Python :: 3.10
Classifier: Programming Language :: Python :: 3.11
Classifier: Programming Language :: Python :: 3.12
Classifier: Topic :: Scientific/Engineering :: Artificial Intelligence
Classifier: Topic :: Internet :: WWW/HTTP :: Indexing/Search
Classifier: Topic :: Software Development :: Libraries :: Python Modules
Classifier: Topic :: System :: Monitoring
Classifier: Topic :: Database :: Database Engines/Servers
Classifier: Environment :: Web Environment
Classifier: Framework :: Flask
Requires-Python: >=3.10
License-File: LICENSE
Requires-Dist: scrapy>=2.10.0
Requires-Dist: requests>=2.31.0
Requires-Dist: beautifulsoup4>=4.12.0
Requires-Dist: pandas>=2.0.0
Requires-Dist: flask>=2.3.0
Requires-Dist: prometheus-client>=0.17.0
Requires-Dist: psutil>=5.9.0
Requires-Dist: configparser>=5.0.0
Requires-Dist: aiohttp>=3.8.0
Requires-Dist: lxml>=4.9.0
Requires-Dist: python-dateutil>=2.8.0
Requires-Dist: click>=8.0.0
Requires-Dist: rich>=13.0.0
Requires-Dist: loguru>=0.7.0
Provides-Extra: monitoring
Requires-Dist: prometheus-client>=0.17.0; extra == "monitoring"
Requires-Dist: psutil>=5.9.0; extra == "monitoring"
Requires-Dist: grafana-api>=1.0.3; extra == "monitoring"
Provides-Extra: enterprise
Requires-Dist: redis>=4.5.0; extra == "enterprise"
Requires-Dist: celery>=5.3.0; extra == "enterprise"
Requires-Dist: gunicorn>=21.0.0; extra == "enterprise"
Provides-Extra: dev
Requires-Dist: pytest>=7.0.0; extra == "dev"
Requires-Dist: pytest-cov>=4.0.0; extra == "dev"
Requires-Dist: black>=23.0.0; extra == "dev"
Requires-Dist: flake8>=6.0.0; extra == "dev"
Requires-Dist: mypy>=1.0.0; extra == "dev"
Requires-Dist: pre-commit>=3.0.0; extra == "dev"
Provides-Extra: docs
Requires-Dist: sphinx>=7.0.0; extra == "docs"
Requires-Dist: sphinx-rtd-theme>=1.3.0; extra == "docs"
Requires-Dist: myst-parser>=2.0.0; extra == "docs"
Dynamic: author
Dynamic: home-page
Dynamic: license-file
Dynamic: requires-python
